pvpcbill/__init__.py
pvpcbill/base.py
pvpcbill/handler.py
pvpcbill/helpers.py
pvpcbill/models.py
pvpcbill/official.py
pvpcbill/text_bill.py
pvpcbill-1.0.0.dist-info/LICENSE
pvpcbill-1.0.0.dist-info/WHEEL
pvpcbill-1.0.0.dist-info/METADATA
pvpcbill-1.0.0.dist-info/RECORD
