Metadata-Version: 2.1
Name: pvpcbill
Version: 1.0.0
Summary: Electrical billing for small consumers in Spain using PVPC
Home-page: https://github.com/azogue/pvpcbill
License: MIT
Author: Eugenio Panadero
Author-email: eugenio.panadero@gmail.com
Requires-Python: >=3.7,<4.0
Classifier: License :: OSI Approved :: MIT License
Classifier: Programming Language :: Python :: 3
Classifier: Programming Language :: Python :: 3.7
Classifier: Programming Language :: Python :: 3.8
Requires-Dist: aiopvpc (==2.0.1)
Requires-Dist: cattrs (>=1.0.0,<2.0.0)
Requires-Dist: matplotlib (>=3.2.1,<4.0.0)
Requires-Dist: pandas (>=1.0.3,<2.0.0)
Project-URL: Repository, https://github.com/azogue/pvpcbill
